{
  "asof_date": "2026-04-15",
  "latest": [
    {
      "sector": "Healthcare",
      "vw_icc": 0.09535799182538172,
      "ew_icc": 0.09893465188199205,
      "n_items": 256.0,
      "date": "2026-04-15",
      "source_file": "data/202604/icc_live_usall_2026_0415_r1.csv"
    },
    {
      "sector": "Consumer Cyclical",
      "vw_icc": 0.09473757812077588,
      "ew_icc": 0.11749644482987996,
      "n_items": 334.0,
      "date": "2026-04-15",
      "source_file": "data/202604/icc_live_usall_2026_0415_r1.csv"
    },
    {
      "sector": "Financial Services",
      "vw_icc": 0.09048234959535006,
      "ew_icc": 0.11954409932308509,
      "n_items": 515.0,
      "date": "2026-04-15",
      "source_file": "data/202604/icc_live_usall_2026_0415_r1.csv"
    },
    {
      "sector": "Energy",
      "vw_icc": 0.08189362446415702,
      "ew_icc": 0.10895902103232877,
      "n_items": 186.0,
      "date": "2026-04-15",
      "source_file": "data/202604/icc_live_usall_2026_0415_r1.csv"
    },
    {
      "sector": "Technology",
      "vw_icc": 0.08110708971210549,
      "ew_icc": 0.09735571653718333,
      "n_items": 375.0,
      "date": "2026-04-15",
      "source_file": "data/202604/icc_live_usall_2026_0415_r1.csv"
    },
    {
      "sector": "Basic Materials",
      "vw_icc": 0.0810829259016994,
      "ew_icc": 0.10982358974848422,
      "n_items": 166.0,
      "date": "2026-04-15",
      "source_file": "data/202604/icc_live_usall_2026_0415_r1.csv"
    },
    {
      "sector": "Utilities",
      "vw_icc": 0.07737848987916464,
      "ew_icc": 0.0855469388748178,
      "n_items": 80.0,
      "date": "2026-04-15",
      "source_file": "data/202604/icc_live_usall_2026_0415_r1.csv"
    },
    {
      "sector": "Consumer Defensive",
      "vw_icc": 0.07453143017200735,
      "ew_icc": 0.10853370051568678,
      "n_items": 135.0,
      "date": "2026-04-15",
      "source_file": "data/202604/icc_live_usall_2026_0415_r1.csv"
    },
    {
      "sector": "Industrials",
      "vw_icc": 0.06982600993979975,
      "ew_icc": 0.09065118477383018,
      "n_items": 383.0,
      "date": "2026-04-15",
      "source_file": "data/202604/icc_live_usall_2026_0415_r1.csv"
    },
    {
      "sector": "Communication Services",
      "vw_icc": 0.068971192307244,
      "ew_icc": 0.12579361946736836,
      "n_items": 124.0,
      "date": "2026-04-15",
      "source_file": "data/202604/icc_live_usall_2026_0415_r1.csv"
    },
    {
      "sector": "Real Estate",
      "vw_icc": 0.05848641035208302,
      "ew_icc": 0.0931128539073337,
      "n_items": 164.0,
      "date": "2026-04-15",
      "source_file": "data/202604/icc_live_usall_2026_0415_r1.csv"
    }
  ],
  "daily": [
    {
      "date": "2025-10-28",
      "summary_icc": 0.07718233986975094,
      "n_groups": 11,
      "source_file": "data/202510/icc_live_usall_2025_1028.csv"
    },
    {
      "date": "2025-10-29",
      "summary_icc": 0.07747076032843946,
      "n_groups": 11,
      "source_file": "data/202510/icc_live_usall_2025_1029.csv"
    },
    {
      "date": "2025-10-30",
      "summary_icc": 0.0781446868488124,
      "n_groups": 11,
      "source_file": "data/202510/icc_live_usall_2025_1030.csv"
    },
    {
      "date": "2025-11-01",
      "summary_icc": 0.0779473501890711,
      "n_groups": 11,
      "source_file": "data/202510/icc_live_usall_2025_1031.csv"
    },
    {
      "date": "2025-11-03",
      "summary_icc": 0.07846323662948468,
      "n_groups": 11,
      "source_file": "data/202511/icc_live_usall_2025_1103.csv"
    },
    {
      "date": "2025-11-04",
      "summary_icc": 0.07845742349428687,
      "n_groups": 11,
      "source_file": "data/202511/icc_live_usall_2025_1104.csv"
    },
    {
      "date": "2025-11-05",
      "summary_icc": 0.07816014335613068,
      "n_groups": 11,
      "source_file": "data/202511/icc_live_usall_2025_1105.csv"
    },
    {
      "date": "2025-11-06",
      "summary_icc": 0.07853645570527021,
      "n_groups": 11,
      "source_file": "data/202511/icc_live_usall_2025_1106.csv"
    },
    {
      "date": "2025-11-07",
      "summary_icc": 0.07810494755182756,
      "n_groups": 11,
      "source_file": "data/202511/icc_live_usall_2025_1107.csv"
    },
    {
      "date": "2025-11-10",
      "summary_icc": 0.07750903849483147,
      "n_groups": 11,
      "source_file": "data/202511/icc_live_usall_2025_1110.csv"
    },
    {
      "date": "2025-11-11",
      "summary_icc": 0.07712968514030133,
      "n_groups": 11,
      "source_file": "data/202511/icc_live_usall_2025_1111.csv"
    },
    {
      "date": "2025-11-12",
      "summary_icc": 0.07735222381131684,
      "n_groups": 11,
      "source_file": "data/202511/icc_live_usall_2025_1112.csv"
    },
    {
      "date": "2025-11-13",
      "summary_icc": 0.0780334295841904,
      "n_groups": 11,
      "source_file": "data/202511/icc_live_usall_2025_1113.csv"
    },
    {
      "date": "2025-11-14",
      "summary_icc": 0.0782129122969894,
      "n_groups": 11,
      "source_file": "data/202511/icc_live_usall_2025_1114.csv"
    },
    {
      "date": "2025-11-17",
      "summary_icc": 0.07827954149246254,
      "n_groups": 11,
      "source_file": "data/202511/icc_live_usall_2025_1117.csv"
    },
    {
      "date": "2025-11-18",
      "summary_icc": 0.07826823474079897,
      "n_groups": 11,
      "source_file": "data/202511/icc_live_usall_2025_1118.csv"
    },
    {
      "date": "2025-11-19",
      "summary_icc": 0.07822893168600575,
      "n_groups": 11,
      "source_file": "data/202511/icc_live_usall_2025_1119.csv"
    },
    {
      "date": "2025-11-20",
      "summary_icc": 0.07899056954476939,
      "n_groups": 11,
      "source_file": "data/202511/icc_live_usall_2025_1120.csv"
    },
    {
      "date": "2025-11-25",
      "summary_icc": 0.07804779160542895,
      "n_groups": 11,
      "source_file": "data/202511/icc_live_usall_2025_1124.csv"
    },
    {
      "date": "2025-11-26",
      "summary_icc": 0.0774414593388371,
      "n_groups": 11,
      "source_file": "data/202511/icc_live_usall_2025_1126.csv"
    },
    {
      "date": "2025-11-27",
      "summary_icc": 0.07742517836414747,
      "n_groups": 11,
      "source_file": "data/202511/icc_live_usall_2025_1127.csv"
    },
    {
      "date": "2025-11-28",
      "summary_icc": 0.07712770241303778,
      "n_groups": 11,
      "source_file": "data/202511/icc_live_usall_2025_1128.csv"
    },
    {
      "date": "2025-12-01",
      "summary_icc": 0.07745823286563135,
      "n_groups": 11,
      "source_file": "data/202512/icc_live_usall_2025_1201.csv"
    },
    {
      "date": "2025-12-02",
      "summary_icc": 0.0776280440084956,
      "n_groups": 11,
      "source_file": "data/202512/icc_live_usall_2025_1202.csv"
    },
    {
      "date": "2025-12-03",
      "summary_icc": 0.07717121604337096,
      "n_groups": 11,
      "source_file": "data/202512/icc_live_usall_2025_1203.csv"
    },
    {
      "date": "2025-12-04",
      "summary_icc": 0.0772118840577313,
      "n_groups": 11,
      "source_file": "data/202512/icc_live_usall_2025_1204.csv"
    },
    {
      "date": "2025-12-05",
      "summary_icc": 0.07755989683542847,
      "n_groups": 11,
      "source_file": "data/202512/icc_live_usall_2025_1205.csv"
    },
    {
      "date": "2025-12-08",
      "summary_icc": 0.07797050881336488,
      "n_groups": 11,
      "source_file": "data/202512/icc_live_usall_2025_1208.csv"
    },
    {
      "date": "2025-12-09",
      "summary_icc": 0.07798608854636038,
      "n_groups": 11,
      "source_file": "data/202512/icc_live_usall_2025_1209.csv"
    },
    {
      "date": "2025-12-10",
      "summary_icc": 0.07921375839208739,
      "n_groups": 11,
      "source_file": "data/202512/icc_live_usall_2025_1210.csv"
    },
    {
      "date": "2025-12-11",
      "summary_icc": 0.07888689584904991,
      "n_groups": 11,
      "source_file": "data/202512/icc_live_usall_2025_1211.csv"
    },
    {
      "date": "2025-12-12",
      "summary_icc": 0.07922567713006108,
      "n_groups": 11,
      "source_file": "data/202512/icc_live_usall_2025_1212.csv"
    },
    {
      "date": "2025-12-15",
      "summary_icc": 0.07922047888457423,
      "n_groups": 11,
      "source_file": "data/202512/icc_live_usall_2025_1215.csv"
    },
    {
      "date": "2025-12-16",
      "summary_icc": 0.07968718668808271,
      "n_groups": 11,
      "source_file": "data/202512/icc_live_usall_2025_1216.csv"
    },
    {
      "date": "2025-12-17",
      "summary_icc": 0.07994394592480422,
      "n_groups": 11,
      "source_file": "data/202512/icc_live_usall_2025_1217.csv"
    },
    {
      "date": "2025-12-18",
      "summary_icc": 0.0798948938484372,
      "n_groups": 11,
      "source_file": "data/202512/icc_live_usall_2025_1218.csv"
    },
    {
      "date": "2025-12-19",
      "summary_icc": 0.07972667003742827,
      "n_groups": 11,
      "source_file": "data/202512/icc_live_usall_2025_1219.csv"
    },
    {
      "date": "2025-12-22",
      "summary_icc": 0.07931788052729385,
      "n_groups": 11,
      "source_file": "data/202512/icc_live_usall_2025_1222.csv"
    },
    {
      "date": "2025-12-23",
      "summary_icc": 0.07917574186221092,
      "n_groups": 11,
      "source_file": "data/202512/icc_live_usall_2025_1223.csv"
    },
    {
      "date": "2025-12-24",
      "summary_icc": 0.07899924124882197,
      "n_groups": 11,
      "source_file": "data/202512/icc_live_usall_2025_1224.csv"
    },
    {
      "date": "2025-12-25",
      "summary_icc": 0.07898986316753678,
      "n_groups": 11,
      "source_file": "data/202512/icc_live_usall_2025_1225.csv"
    },
    {
      "date": "2025-12-26",
      "summary_icc": 0.07905325959577918,
      "n_groups": 11,
      "source_file": "data/202512/icc_live_usall_2025_1226.csv"
    },
    {
      "date": "2025-12-29",
      "summary_icc": 0.07916764071073325,
      "n_groups": 11,
      "source_file": "data/202512/icc_live_usall_2025_1229.csv"
    },
    {
      "date": "2025-12-30",
      "summary_icc": 0.07914703555692261,
      "n_groups": 11,
      "source_file": "data/202512/icc_live_usall_2025_1230.csv"
    },
    {
      "date": "2025-12-31",
      "summary_icc": 0.07955566002503905,
      "n_groups": 11,
      "source_file": "data/202512/icc_live_usall_2025_1231.csv"
    },
    {
      "date": "2026-01-01",
      "summary_icc": 0.07904382525678574,
      "n_groups": 11,
      "source_file": "data/202601/icc_live_usall_2026_0101.csv"
    },
    {
      "date": "2026-01-02",
      "summary_icc": 0.07859131383585699,
      "n_groups": 11,
      "source_file": "data/202601/icc_live_usall_2026_0102.csv"
    },
    {
      "date": "2026-01-06",
      "summary_icc": 0.07685165367299022,
      "n_groups": 11,
      "source_file": "data/202601/icc_live_usall_2026_0106_r1.csv"
    },
    {
      "date": "2026-01-07",
      "summary_icc": 0.07715633918985428,
      "n_groups": 11,
      "source_file": "data/202601/icc_live_usall_2026_0107_r1.csv"
    },
    {
      "date": "2026-01-08",
      "summary_icc": 0.0767584149030369,
      "n_groups": 11,
      "source_file": "data/202601/icc_live_usall_2026_0108_r1.csv"
    },
    {
      "date": "2026-01-09",
      "summary_icc": 0.07635688137248624,
      "n_groups": 11,
      "source_file": "data/202601/icc_live_usall_2026_0109_r1.csv"
    },
    {
      "date": "2026-01-12",
      "summary_icc": 0.07614058597194134,
      "n_groups": 11,
      "source_file": "data/202601/icc_live_usall_2026_0112_r1.csv"
    },
    {
      "date": "2026-01-13",
      "summary_icc": 0.07609286715856346,
      "n_groups": 11,
      "source_file": "data/202601/icc_live_usall_2026_0113_r1.csv"
    },
    {
      "date": "2026-01-14",
      "summary_icc": 0.07578854442530103,
      "n_groups": 11,
      "source_file": "data/202601/icc_live_usall_2026_0114_r1.csv"
    },
    {
      "date": "2026-01-15",
      "summary_icc": 0.07585894989581833,
      "n_groups": 11,
      "source_file": "data/202601/icc_live_usall_2026_0115_r1.csv"
    },
    {
      "date": "2026-01-16",
      "summary_icc": 0.07598321230535089,
      "n_groups": 11,
      "source_file": "data/202601/icc_live_usall_2026_0116_r1.csv"
    },
    {
      "date": "2026-01-19",
      "summary_icc": 0.07603140731979198,
      "n_groups": 11,
      "source_file": "data/202601/icc_live_usall_2026_0119_r1.csv"
    },
    {
      "date": "2026-01-20",
      "summary_icc": 0.07687991785564136,
      "n_groups": 11,
      "source_file": "data/202601/icc_live_usall_2026_0120_r1.csv"
    },
    {
      "date": "2026-01-21",
      "summary_icc": 0.07618143129207205,
      "n_groups": 11,
      "source_file": "data/202601/icc_live_usall_2026_0121_r1.csv"
    },
    {
      "date": "2026-01-22",
      "summary_icc": 0.07602065449928018,
      "n_groups": 11,
      "source_file": "data/202601/icc_live_usall_2026_0122_r1.csv"
    },
    {
      "date": "2026-01-23",
      "summary_icc": 0.07607736451941757,
      "n_groups": 11,
      "source_file": "data/202601/icc_live_usall_2026_0123_r1.csv"
    },
    {
      "date": "2026-01-26",
      "summary_icc": 0.07609927093411648,
      "n_groups": 11,
      "source_file": "data/202601/icc_live_usall_2026_0126_r1.csv"
    },
    {
      "date": "2026-01-27",
      "summary_icc": 0.07626270884301564,
      "n_groups": 11,
      "source_file": "data/202601/icc_live_usall_2026_0127_r1.csv"
    },
    {
      "date": "2026-01-28",
      "summary_icc": 0.07649933637616982,
      "n_groups": 11,
      "source_file": "data/202601/icc_live_usall_2026_0128_r1.csv"
    },
    {
      "date": "2026-01-29",
      "summary_icc": 0.07568816784202713,
      "n_groups": 11,
      "source_file": "data/202601/icc_live_usall_2026_0129_r1.csv"
    },
    {
      "date": "2026-01-30",
      "summary_icc": 0.07668821556074162,
      "n_groups": 11,
      "source_file": "data/202601/icc_live_usall_2026_0130_r1.csv"
    },
    {
      "date": "2026-02-03",
      "summary_icc": 0.07808948350223109,
      "n_groups": 11,
      "source_file": "data/202602/icc_live_usall_2026_0203_r1.csv"
    },
    {
      "date": "2026-02-04",
      "summary_icc": 0.07924872334884778,
      "n_groups": 11,
      "source_file": "data/202602/icc_live_usall_2026_0204_r1.csv"
    },
    {
      "date": "2026-02-05",
      "summary_icc": 0.08081106986092677,
      "n_groups": 11,
      "source_file": "data/202602/icc_live_usall_2026_0205_r1.csv"
    },
    {
      "date": "2026-02-06",
      "summary_icc": 0.08086777363890241,
      "n_groups": 11,
      "source_file": "data/202602/icc_live_usall_2026_0206_r1.csv"
    },
    {
      "date": "2026-02-09",
      "summary_icc": 0.08048979663859736,
      "n_groups": 11,
      "source_file": "data/202602/icc_live_usall_2026_0209_r1.csv"
    },
    {
      "date": "2026-02-10",
      "summary_icc": 0.08051002475905869,
      "n_groups": 11,
      "source_file": "data/202602/icc_live_usall_2026_0210_r1.csv"
    },
    {
      "date": "2026-02-11",
      "summary_icc": 0.08076821092236833,
      "n_groups": 11,
      "source_file": "data/202602/icc_live_usall_2026_0211_r1.csv"
    },
    {
      "date": "2026-02-12",
      "summary_icc": 0.08171956810871114,
      "n_groups": 11,
      "source_file": "data/202602/icc_live_usall_2026_0212_r1.csv"
    },
    {
      "date": "2026-02-13",
      "summary_icc": 0.0810866574874647,
      "n_groups": 11,
      "source_file": "data/202602/icc_live_usall_2026_0213_r1.csv"
    },
    {
      "date": "2026-02-16",
      "summary_icc": 0.08146333672072892,
      "n_groups": 11,
      "source_file": "data/202602/icc_live_usall_2026_0216_r1.csv"
    },
    {
      "date": "2026-02-17",
      "summary_icc": 0.08163496570991874,
      "n_groups": 11,
      "source_file": "data/202602/icc_live_usall_2026_0217_r1.csv"
    },
    {
      "date": "2026-02-18",
      "summary_icc": 0.08128942945578274,
      "n_groups": 11,
      "source_file": "data/202602/icc_live_usall_2026_0218_r1.csv"
    },
    {
      "date": "2026-02-19",
      "summary_icc": 0.08072731951346691,
      "n_groups": 11,
      "source_file": "data/202602/icc_live_usall_2026_0219_r1.csv"
    },
    {
      "date": "2026-02-20",
      "summary_icc": 0.08003503449251367,
      "n_groups": 11,
      "source_file": "data/202602/icc_live_usall_2026_0220_r1.csv"
    },
    {
      "date": "2026-02-23",
      "summary_icc": 0.07999161509051772,
      "n_groups": 11,
      "source_file": "data/202602/icc_live_usall_2026_0223_r1.csv"
    },
    {
      "date": "2026-02-24",
      "summary_icc": 0.07964651718061239,
      "n_groups": 11,
      "source_file": "data/202602/icc_live_usall_2026_0224_r1.csv"
    },
    {
      "date": "2026-02-25",
      "summary_icc": 0.07972321655516533,
      "n_groups": 11,
      "source_file": "data/202602/icc_live_usall_2026_0225_r1.csv"
    },
    {
      "date": "2026-02-26",
      "summary_icc": 0.07929311965632325,
      "n_groups": 11,
      "source_file": "data/202602/icc_live_usall_2026_0226_r1.csv"
    },
    {
      "date": "2026-02-27",
      "summary_icc": 0.0791148646428733,
      "n_groups": 11,
      "source_file": "data/202602/icc_live_usall_2026_0227_r1.csv"
    },
    {
      "date": "2026-03-02",
      "summary_icc": 0.07880325156791158,
      "n_groups": 11,
      "source_file": "data/202603/icc_live_usall_2026_0302_r1.csv"
    },
    {
      "date": "2026-03-03",
      "summary_icc": 0.07955399301543825,
      "n_groups": 11,
      "source_file": "data/202603/icc_live_usall_2026_0303_r1.csv"
    },
    {
      "date": "2026-03-04",
      "summary_icc": 0.07950849011213544,
      "n_groups": 11,
      "source_file": "data/202603/icc_live_usall_2026_0304_r1.csv"
    },
    {
      "date": "2026-03-05",
      "summary_icc": 0.08050184889608068,
      "n_groups": 11,
      "source_file": "data/202603/icc_live_usall_2026_0305_r1.csv"
    },
    {
      "date": "2026-03-06",
      "summary_icc": 0.08137405552561582,
      "n_groups": 11,
      "source_file": "data/202603/icc_live_usall_2026_0306_r1.csv"
    },
    {
      "date": "2026-03-09",
      "summary_icc": 0.0810090089375022,
      "n_groups": 11,
      "source_file": "data/202603/icc_live_usall_2026_0309_r1.csv"
    },
    {
      "date": "2026-03-10",
      "summary_icc": 0.08116341080183044,
      "n_groups": 11,
      "source_file": "data/202603/icc_live_usall_2026_0310_r1.csv"
    },
    {
      "date": "2026-03-11",
      "summary_icc": 0.08109411125003094,
      "n_groups": 11,
      "source_file": "data/202603/icc_live_usall_2026_0311_r1.csv"
    },
    {
      "date": "2026-03-12",
      "summary_icc": 0.08148646370457781,
      "n_groups": 11,
      "source_file": "data/202603/icc_live_usall_2026_0312_r1.csv"
    },
    {
      "date": "2026-03-13",
      "summary_icc": 0.0815045581157306,
      "n_groups": 11,
      "source_file": "data/202603/icc_live_usall_2026_0313_r1.csv"
    },
    {
      "date": "2026-03-16",
      "summary_icc": 0.08021615885432352,
      "n_groups": 11,
      "source_file": "data/202603/icc_live_usall_2026_0316_r1.csv"
    },
    {
      "date": "2026-03-17",
      "summary_icc": 0.08020577273722952,
      "n_groups": 11,
      "source_file": "data/202603/icc_live_usall_2026_0317_r1.csv"
    },
    {
      "date": "2026-03-18",
      "summary_icc": 0.08101863492758384,
      "n_groups": 11,
      "source_file": "data/202603/icc_live_usall_2026_0318_r1.csv"
    },
    {
      "date": "2026-03-19",
      "summary_icc": 0.08131058670213448,
      "n_groups": 11,
      "source_file": "data/202603/icc_live_usall_2026_0319_r1.csv"
    },
    {
      "date": "2026-03-20",
      "summary_icc": 0.0824996851294562,
      "n_groups": 11,
      "source_file": "data/202603/icc_live_usall_2026_0320_r1.csv"
    },
    {
      "date": "2026-03-23",
      "summary_icc": 0.08177026845716563,
      "n_groups": 11,
      "source_file": "data/202603/icc_live_usall_2026_0323_r1.csv"
    },
    {
      "date": "2026-03-24",
      "summary_icc": 0.08155490858819069,
      "n_groups": 11,
      "source_file": "data/202603/icc_live_usall_2026_0324_r1.csv"
    },
    {
      "date": "2026-03-25",
      "summary_icc": 0.08123994120880985,
      "n_groups": 11,
      "source_file": "data/202603/icc_live_usall_2026_0325_r1.csv"
    },
    {
      "date": "2026-03-26",
      "summary_icc": 0.08180349382376509,
      "n_groups": 11,
      "source_file": "data/202603/icc_live_usall_2026_0326_r1.csv"
    },
    {
      "date": "2026-03-27",
      "summary_icc": 0.08229654138799244,
      "n_groups": 11,
      "source_file": "data/202603/icc_live_usall_2026_0327_r1.csv"
    },
    {
      "date": "2026-03-30",
      "summary_icc": 0.08268712914853399,
      "n_groups": 11,
      "source_file": "data/202603/icc_live_usall_2026_0330_r1.csv"
    },
    {
      "date": "2026-03-31",
      "summary_icc": 0.08153501496920224,
      "n_groups": 11,
      "source_file": "data/202603/icc_live_usall_2026_0331_r1.csv"
    },
    {
      "date": "2026-04-01",
      "summary_icc": 0.08122546776797447,
      "n_groups": 11,
      "source_file": "data/202604/icc_live_usall_2026_0401_r1.csv"
    },
    {
      "date": "2026-04-02",
      "summary_icc": 0.08118870559953831,
      "n_groups": 11,
      "source_file": "data/202604/icc_live_usall_2026_0402_r1.csv"
    },
    {
      "date": "2026-04-03",
      "summary_icc": 0.08097963342456463,
      "n_groups": 11,
      "source_file": "data/202604/icc_live_usall_2026_0403_r1.csv"
    },
    {
      "date": "2026-04-06",
      "summary_icc": 0.08079170598581663,
      "n_groups": 11,
      "source_file": "data/202604/icc_live_usall_2026_0406_r1.csv"
    },
    {
      "date": "2026-04-07",
      "summary_icc": 0.0805817763869975,
      "n_groups": 11,
      "source_file": "data/202604/icc_live_usall_2026_0407_r1.csv"
    },
    {
      "date": "2026-04-08",
      "summary_icc": 0.07947658955541564,
      "n_groups": 11,
      "source_file": "data/202604/icc_live_usall_2026_0408_r1.csv"
    },
    {
      "date": "2026-04-09",
      "summary_icc": 0.07966554082038853,
      "n_groups": 11,
      "source_file": "data/202604/icc_live_usall_2026_0409_r1.csv"
    },
    {
      "date": "2026-04-10",
      "summary_icc": 0.07994021437160158,
      "n_groups": 11,
      "source_file": "data/202604/icc_live_usall_2026_0410_r1.csv"
    },
    {
      "date": "2026-04-13",
      "summary_icc": 0.07955096531141362,
      "n_groups": 11,
      "source_file": "data/202604/icc_live_usall_2026_0413_r2.csv"
    },
    {
      "date": "2026-04-14",
      "summary_icc": 0.07931652900790975,
      "n_groups": 11,
      "source_file": "data/202604/icc_live_usall_2026_0414_r1.csv"
    },
    {
      "date": "2026-04-15",
      "summary_icc": 0.07944137202452439,
      "n_groups": 11,
      "source_file": "data/202604/icc_live_usall_2026_0415_r1.csv"
    }
  ],
  "monthly": [
    {
      "date": "2025-10-30",
      "summary_icc": 0.0781446868488124,
      "n_groups": 11,
      "source_file": "data/202510/icc_live_usall_2025_1030.csv",
      "yyyymm": "2025-10"
    },
    {
      "date": "2025-11-28",
      "summary_icc": 0.07712770241303778,
      "n_groups": 11,
      "source_file": "data/202511/icc_live_usall_2025_1128.csv",
      "yyyymm": "2025-11"
    },
    {
      "date": "2025-12-31",
      "summary_icc": 0.07955566002503905,
      "n_groups": 11,
      "source_file": "data/202512/icc_live_usall_2025_1231.csv",
      "yyyymm": "2025-12"
    },
    {
      "date": "2026-01-30",
      "summary_icc": 0.07668821556074162,
      "n_groups": 11,
      "source_file": "data/202601/icc_live_usall_2026_0130_r1.csv",
      "yyyymm": "2026-01"
    },
    {
      "date": "2026-02-27",
      "summary_icc": 0.0791148646428733,
      "n_groups": 11,
      "source_file": "data/202602/icc_live_usall_2026_0227_r1.csv",
      "yyyymm": "2026-02"
    },
    {
      "date": "2026-03-31",
      "summary_icc": 0.08153501496920224,
      "n_groups": 11,
      "source_file": "data/202603/icc_live_usall_2026_0331_r1.csv",
      "yyyymm": "2026-03"
    },
    {
      "date": "2026-04-15",
      "summary_icc": 0.07944137202452439,
      "n_groups": 11,
      "source_file": "data/202604/icc_live_usall_2026_0415_r1.csv",
      "yyyymm": "2026-04"
    }
  ],
  "downloads": [
    {
      "label": "Daily history CSV",
      "path": "./data/downloads/industry_daily_history.csv"
    },
    {
      "label": "Monthly history CSV",
      "path": "./data/downloads/industry_monthly_history.csv"
    },
    {
      "label": "Latest breakdown CSV",
      "path": "./data/downloads/industry_latest.csv"
    }
  ],
  "latest_summary": 0.07944137202452439
}